lobotomy/__init__.py
lobotomy/_cli/__init__.py
lobotomy/_cli/_adder.py
lobotomy/_cli/_definitions.py
lobotomy/_cli/_parsing.py
lobotomy/_clients/__init__.py
lobotomy/_clients/_casting.py
lobotomy/_clients/_definitions.py
lobotomy/_clients/_validation.py
lobotomy/_exceptions.py
lobotomy/_fio.py
lobotomy/_mocking.py
lobotomy/_mutator.py
lobotomy/_services/__init__.py
lobotomy/_services/_augmentations/__init__.py
lobotomy/_services/_augmentations/lambda.yaml
lobotomy/_services/_augmentations/s3.yaml
lobotomy/_services/_definitions.py
lobotomy/_services/_formatting.py
lobotomy/_sessions.py
lobotomy/_yaml.py
lobotomy-0.3.14.dist-info/LICENSE
lobotomy-0.3.14.dist-info/METADATA
lobotomy-0.3.14.dist-info/WHEEL
lobotomy-0.3.14.dist-info/entry_points.txt
lobotomy-0.3.14.dist-info/RECORD
