Metadata-Version: 2.1
Name: lobotomy
Version: 0.3.14
Summary: Boto3 low-level client mocking library.
Home-page: https://gitlab.com/rocket-boosters/lobotomy
License: MIT
Keywords: aws,boto3,botocore,testing
Author: Scott Ernst
Author-email: swernst@gmail.com
Requires-Python: >=3.8.0,<4.0.0
Classifier: Development Status :: 4 - Beta
Classifier: Environment :: Console
Classifier: Intended Audience :: Developers
Classifier: License :: OSI Approved :: MIT License
Classifier: Programming Language :: Python :: 3
Classifier: Programming Language :: Python :: 3.8
Classifier: Programming Language :: Python :: 3.9
Classifier: Programming Language :: Python :: 3.10
Classifier: Programming Language :: Python :: 3.11
Classifier: Programming Language :: Python :: 3.12
Classifier: Topic :: Software Development :: Testing
Classifier: Topic :: Software Development :: Testing :: Mocking
Classifier: Topic :: Software Development :: Testing :: Unit
Classifier: Topic :: Utilities
Classifier: Typing :: Typed
Requires-Dist: PyYAML (>=5.3.0)
Requires-Dist: boto3 (>=1.16.0)
Requires-Dist: python-dateutil (>=2.8.0)
Requires-Dist: toml (>=0.10.0)
Project-URL: Documentation, https://gitlab.com/rocket-boosters/lobotomy
Project-URL: Repository, https://gitlab.com/rocket-boosters/lobotomy
